simple_ecc/__init__.py
simple_ecc/ecc.py
simple_ecc-0.1.1.dist-info/LICENSE
simple_ecc-0.1.1.dist-info/METADATA
simple_ecc-0.1.1.dist-info/WHEEL
simple_ecc-0.1.1.dist-info/top_level.txt
simple_ecc-0.1.1.dist-info/RECORD
