Metadata-Version: 2.1
Name: simple-ecc
Version: 0.1.1
Summary: A simple elliptic curve cryptography library
Home-page: https://github.com/mohdluqman/simple-ecc
Author: Mohammad Luqman, Salman Ali, Faisal Anwer
Author-email: Mohammad Luqman <luqman.geeky@gmail.com>, Salman Ali <salmanali.amu@gmail.com>, Faisal Anwer <faisalanwer.cs@amu.ac.in>
License: MIT
Project-URL: Homepage, https://github.com/mohdluqman/simple-ecc
Classifier: Programming Language :: Python :: 3
Classifier: License :: OSI Approved :: MIT License
Classifier: Operating System :: OS Independent
Requires-Python: >=3.6
License-File: LICENSE
